<?xml version="1.0"?>
<!DOCTYPE hibernate-mapping PUBLIC "-//Hibernate/Hibernate Mapping DTD 3.0//EN"
"http://www.hibernate.org/dtd/hibernate-mapping-3.0.dtd">
<!-- Generated Oct 29, 2013 12:06:15 PM by Hibernate Tools 3.4.0.CR1 -->
<hibernate-mapping default-lazy="false">
    <class name="org.wattdepot.datamodel.CollectorMetaData" table="SENSORPROCESS">
        <id name="id" type="java.lang.String">
            <column name="ID" />
            <generator class="assigned" />
        </id>
        <property name="name" type = "java.lang.String">
            <column name="NAME" />
        </property>
        <many-to-one name="sensor" class="org.wattdepot.datamodel.Sensor" fetch="join">
            <column name="SENSOR" />
        </many-to-one>
        <property name="pollingInterval" type="java.lang.Long">
            <column name="POLLINGINTERVAL" />
        </property>
        <property name="depositoryId" type="java.lang.String">
            <column name="DEPOSITORYID" />
        </property>
        <set name="properties" table="PROPERTY" inverse="false" lazy="false">
            <key>
                <column name="SENSORPROCESS_ID" />
            </key>
            <one-to-many class="org.wattdepot.datamodel.Property" />
        </set>
        <many-to-one name="owner" class="org.wattdepot.datamodel.UserGroup" fetch="join">
            <column name="OWNER" />
        </many-to-one>
    </class>
</hibernate-mapping>
